Metadata-Version: 2.1
Name: random-quote-generator-6886754
Version: 0.1.0
Summary: my random quote generaror
License: MIT
Author: Mfana Ronald Conco
Author-email: ronald.conco@mlankatech.co.za
Requires-Python: >=3.9,<4.0
Classifier: License :: OSI Approved :: MIT License
Classifier: Programming Language :: Python :: 3
Classifier: Programming Language :: Python :: 3.10
Classifier: Programming Language :: Python :: 3.9
